insult/__init__.py
insult/insult.py
insult/settings.yml
finnsult-1.11.dist-info/LICENSE.txt
finnsult-1.11.dist-info/METADATA
finnsult-1.11.dist-info/WHEEL
finnsult-1.11.dist-info/entry_points.txt
finnsult-1.11.dist-info/top_level.txt
finnsult-1.11.dist-info/RECORD
