Metadata-Version: 2.1
Name: finnsult
Version: 1.11
Summary: A program to insult people
Home-page: https://the-real-finnventor.github.io/insult/
Author: Finn Everspaugh
Author-email: finnventor@everspaugh.com
Classifier: Programming Language :: Python :: 3
Classifier: License :: OSI Approved :: MIT License
Classifier: Operating System :: MacOS
License-File: LICENSE.txt
Requires-Dist: pyyaml
